[{"id":"taicol-t0048120","source":"taicol","sourceId":"t0048120","scientificName":"Tropodiaptomus oryzanus","synonyms":[],"commonName":{"local":"米粒近鏢水蚤"},"alias":{"local":""},"kingdom":{"scientific":"Animalia","local":"動物界"},"phylum":{"scientific":"Arthropoda","local":"節肢動物門"},"taxonClass":{"scientific":"Copepoda","local":"橈足綱"},"taxonOrder":{"scientific":"Calanoida","local":"哲水蚤目"},"family":{"scientific":"Diaptomidae","local":"鏢水蚤科"},"genus":{"scientific":"Tropodiaptomus","local":"近鏢水蚤屬"},"region":"Taiwan","isEndemic":false,"isAlien":true,"habitat":["freshwater"],"conservationStatus":"N","cites":"","iucn":"","meta":{"alienType":"native","rank":"Species"}},{"id":"taicol-t0062734","source":"taicol","sourceId":"t0062734","scientificName":"Eodiaptomus japonicus","synonyms":[],"commonName":{"local":"日本原鏢水蚤"},"alias":{"local":""},"kingdom":{"scientific":"Animalia","local":"動物界"},"phylum":{"scientific":"Arthropoda","local":"節肢動物門"},"taxonClass":{"scientific":"Copepoda","local":"橈足綱"},"taxonOrder":{"scientific":"Calanoida","local":"哲水蚤目"},"family":{"scientific":"Diaptomidae","local":"鏢水蚤科"},"genus":{"scientific":"Eodiaptomus","local":"原鏢水蚤屬"},"region":"Taiwan","isEndemic":false,"isAlien":true,"habitat":["freshwater"],"conservationStatus":"N","cites":"","iucn":"","meta":{"alienType":"native","rank":"Species"}},{"id":"taicol-t0063309","source":"taicol","sourceId":"t0063309","scientificName":"Eudiaptomus formosus","synonyms":[],"commonName":{"local":"臺灣真鏢水蚤"},"alias":{"local":"台灣真鏢水蚤"},"kingdom":{"scientific":"Animalia","local":"動物界"},"phylum":{"scientific":"Arthropoda","local":"節肢動物門"},"taxonClass":{"scientific":"Copepoda","local":"橈足綱"},"taxonOrder":{"scientific":"Calanoida","local":"哲水蚤目"},"family":{"scientific":"Diaptomidae","local":"鏢水蚤科"},"genus":{"scientific":"Eudiaptomus","local":"真鏢水蚤屬"},"region":"Taiwan","isEndemic":false,"isAlien":true,"habitat":["freshwater"],"conservationStatus":"N","cites":"","iucn":"","meta":{"alienType":"native","rank":"Species"}},{"id":"taicol-t0065266","source":"taicol","sourceId":"t0065266","scientificName":"Heliodiaptomus kikuchii","synonyms":[],"commonName":{"local":"鳥啄明鏢水蚤"},"alias":{"local":""},"kingdom":{"scientific":"Animalia","local":"動物界"},"phylum":{"scientific":"Arthropoda","local":"節肢動物門"},"taxonClass":{"scientific":"Copepoda","local":"橈足綱"},"taxonOrder":{"scientific":"Calanoida","local":"哲水蚤目"},"family":{"scientific":"Diaptomidae","local":"鏢水蚤科"},"genus":{"scientific":"Heliodiaptomus","local":"明鏢水蚤屬"},"region":"Taiwan","isEndemic":false,"isAlien":true,"habitat":["freshwater"],"conservationStatus":"N","cites":"","iucn":"","meta":{"alienType":"native","rank":"Species"}},{"id":"taicol-t0070882","source":"taicol","sourceId":"t0070882","scientificName":"Allodiaptomus uenoi","synonyms":[],"commonName":{"local":"臺灣複鏢水蚤"},"alias":{"local":"台灣複鏢水蚤"},"kingdom":{"scientific":"Animalia","local":"動物界"},"phylum":{"scientific":"Arthropoda","local":"節肢動物門"},"taxonClass":{"scientific":"Copepoda","local":"橈足綱"},"taxonOrder":{"scientific":"Calanoida","local":"哲水蚤目"},"family":{"scientific":"Diaptomidae","local":"鏢水蚤科"},"genus":{"scientific":"Allodiaptomus","local":"複鏢水蚤屬"},"region":"Taiwan","isEndemic":false,"isAlien":true,"habitat":["freshwater"],"conservationStatus":"N","cites":"","iucn":"","meta":{"alienType":"native","rank":"Species"}},{"id":"taicol-t0080396","source":"taicol","sourceId":"t0080396","scientificName":"Mongolodiaptomus birulai","synonyms":[],"commonName":{"local":"錐肢蒙鏢水蚤"},"alias":{"local":""},"kingdom":{"scientific":"Animalia","local":"動物界"},"phylum":{"scientific":"Arthropoda","local":"節肢動物門"},"taxonClass":{"scientific":"Copepoda","local":"橈足綱"},"taxonOrder":{"scientific":"Calanoida","local":"哲水蚤目"},"family":{"scientific":"Diaptomidae","local":"鏢水蚤科"},"genus":{"scientific":"Mongolodiaptomus","local":"蒙鏢水蚤屬"},"region":"Taiwan","isEndemic":false,"isAlien":true,"habitat":["freshwater"],"conservationStatus":"N","cites":"","iucn":"","meta":{"alienType":"native","rank":"Species"}},{"id":"taicol-t0080397","source":"taicol","sourceId":"t0080397","scientificName":"Mongolodiaptomus formosanus","synonyms":[],"commonName":{"local":"台蒙鏢水蚤"},"alias":{"local":"臺蒙鏢水蚤"},"kingdom":{"scientific":"Animalia","local":"動物界"},"phylum":{"scientific":"Arthropoda","local":"節肢動物門"},"taxonClass":{"scientific":"Copepoda","local":"橈足綱"},"taxonOrder":{"scientific":"Calanoida","local":"哲水蚤目"},"family":{"scientific":"Diaptomidae","local":"鏢水蚤科"},"genus":{"scientific":"Mongolodiaptomus","local":"蒙鏢水蚤屬"},"region":"Taiwan","isEndemic":false,"isAlien":true,"habitat":["freshwater"],"conservationStatus":"N","cites":"","iucn":"","meta":{"alienType":"native","rank":"Species"}},{"id":"taicol-t0081598","source":"taicol","sourceId":"t0081598","scientificName":"Neutrodiaptomus formosus","synonyms":[],"commonName":{"local":"臺灣胖蕩鏢水蚤"},"alias":{"local":"台灣胖蕩鏢水蚤"},"kingdom":{"scientific":"Animalia","local":"動物界"},"phylum":{"scientific":"Arthropoda","local":"節肢動物門"},"taxonClass":{"scientific":"Copepoda","local":"橈足綱"},"taxonOrder":{"scientific":"Calanoida","local":"哲水蚤目"},"family":{"scientific":"Diaptomidae","local":"鏢水蚤科"},"genus":{"scientific":"Neutrodiaptomus","local":"胖蕩鏢水蚤屬"},"region":"Taiwan","isEndemic":false,"isAlien":true,"habitat":["freshwater"],"conservationStatus":"N","cites":"","iucn":"","meta":{"alienType":"native","rank":"Species"}},{"id":"taicol-t0081599","source":"taicol","sourceId":"t0081599","scientificName":"Neutrodiaptomus tumidus","synonyms":[],"commonName":{"local":"肥胖蕩鏢水蚤"},"alias":{"local":""},"kingdom":{"scientific":"Animalia","local":"動物界"},"phylum":{"scientific":"Arthropoda","local":"節肢動物門"},"taxonClass":{"scientific":"Copepoda","local":"橈足綱"},"taxonOrder":{"scientific":"Calanoida","local":"哲水蚤目"},"family":{"scientific":"Diaptomidae","local":"鏢水蚤科"},"genus":{"scientific":"Neutrodiaptomus","local":"胖蕩鏢水蚤屬"},"region":"Taiwan","isEndemic":false,"isAlien":true,"habitat":["freshwater"],"conservationStatus":"N","cites":"","iucn":"","meta":{"alienType":"native","rank":"Species"}}]