[{"id":"taicol-t0030715","source":"taicol","sourceId":"t0030715","scientificName":"Coscinasterias acutispina","synonyms":[],"commonName":{"local":"尖棘篩海盤車"},"alias":{"local":""},"kingdom":{"scientific":"Animalia","local":"動物界"},"phylum":{"scientific":"Echinodermata","local":"棘皮動物門"},"taxonClass":{"scientific":"Asteroidea","local":"海星綱"},"taxonOrder":{"scientific":"Forcipulatida","local":"鉗棘目"},"family":{"scientific":"Asteriidae","local":"海盤車科"},"genus":{"scientific":"Coscinasterias","local":"篩海盤車屬"},"region":"Taiwan","isEndemic":false,"isAlien":true,"habitat":["marine"],"conservationStatus":"N","cites":"","iucn":"","meta":{"alienType":"native","rank":"Species"}},{"id":"taicol-t0061837","source":"taicol","sourceId":"t0061837","scientificName":"Distolasterias nipon","synonyms":[],"commonName":{"local":"日本長腕海盤車"},"alias":{"local":""},"kingdom":{"scientific":"Animalia","local":"動物界"},"phylum":{"scientific":"Echinodermata","local":"棘皮動物門"},"taxonClass":{"scientific":"Asteroidea","local":"海星綱"},"taxonOrder":{"scientific":"Forcipulatida","local":"鉗棘目"},"family":{"scientific":"Asteriidae","local":"海盤車科"},"genus":{"scientific":"Distolasterias","local":"長腕海盤車屬"},"region":"Taiwan","isEndemic":false,"isAlien":true,"habitat":["marine"],"conservationStatus":"N","cites":"","iucn":"","meta":{"alienType":"native","rank":"Species"}},{"id":"taicol-t0072429","source":"taicol","sourceId":"t0072429","scientificName":"Asterias versicolor","synonyms":[],"commonName":{"local":"異色海盤車"},"alias":{"local":""},"kingdom":{"scientific":"Animalia","local":"動物界"},"phylum":{"scientific":"Echinodermata","local":"棘皮動物門"},"taxonClass":{"scientific":"Asteroidea","local":"海星綱"},"taxonOrder":{"scientific":"Forcipulatida","local":"鉗棘目"},"family":{"scientific":"Asteriidae","local":"海盤車科"},"genus":{"scientific":"Asterias","local":"海盤車屬"},"region":"Taiwan","isEndemic":false,"isAlien":true,"habitat":["marine"],"conservationStatus":"N","cites":"","iucn":"","meta":{"alienType":"native","rank":"Species"}},{"id":"taicol-t0100135","source":"taicol","sourceId":"t0100135","scientificName":"Asterias multifora","synonyms":[],"commonName":{"local":"Asterias multifora"},"alias":{"local":""},"kingdom":{"scientific":"Animalia","local":"動物界"},"phylum":{"scientific":"Echinodermata","local":"棘皮動物門"},"taxonClass":{"scientific":"Asteroidea","local":"海星綱"},"taxonOrder":{"scientific":"Forcipulatida","local":"鉗棘目"},"family":{"scientific":"Asteriidae","local":"海盤車科"},"genus":{"scientific":"Asterias","local":"海盤車屬"},"region":"Taiwan","isEndemic":false,"isAlien":false,"habitat":[],"conservationStatus":"N","cites":"","iucn":"","meta":{"alienType":"","rank":"Species"}},{"id":"taicol-t0123646","source":"taicol","sourceId":"t0123646","scientificName":"Asterias amurensis","synonyms":[],"commonName":{"local":"Asterias amurensis"},"alias":{"local":""},"kingdom":{"scientific":"Animalia","local":"動物界"},"phylum":{"scientific":"Echinodermata","local":"棘皮動物門"},"taxonClass":{"scientific":"Asteroidea","local":"海星綱"},"taxonOrder":{"scientific":"Forcipulatida","local":"鉗棘目"},"family":{"scientific":"Asteriidae","local":"海盤車科"},"genus":{"scientific":"Asterias","local":"海盤車屬"},"region":"Taiwan","isEndemic":false,"isAlien":false,"habitat":[],"conservationStatus":"N","cites":"","iucn":"","meta":{"alienType":"","rank":"Species"}}]