[{"id":"taicol-t0034554","source":"taicol","sourceId":"t0034554","scientificName":"Capnodiastrum sawadae","synonyms":[],"commonName":{"local":"Capnodiastrum sawadae"},"alias":{"local":""},"kingdom":{"scientific":"Fungi","local":"真菌界"},"phylum":{"scientific":"Ascomycota","local":"子囊菌門"},"taxonClass":{"scientific":"Dothideomycetes","local":"座囊菌綱"},"taxonOrder":{"scientific":"","local":""},"family":{"scientific":"Englerulaceae","local":""},"genus":{"scientific":"Capnodiastrum","local":""},"region":"Taiwan","isEndemic":false,"isAlien":true,"habitat":[],"conservationStatus":"N","cites":"","iucn":"","meta":{"alienType":"native","rank":"Species"}},{"id":"taicol-t0043749","source":"taicol","sourceId":"t0043749","scientificName":"Rhytidenglerula trematis","synonyms":[],"commonName":{"local":"山黃麻皺膠皿煤菌"},"alias":{"local":""},"kingdom":{"scientific":"Fungi","local":"真菌界"},"phylum":{"scientific":"Ascomycota","local":"子囊菌門"},"taxonClass":{"scientific":"Dothideomycetes","local":"座囊菌綱"},"taxonOrder":{"scientific":"","local":""},"family":{"scientific":"Englerulaceae","local":""},"genus":{"scientific":"Rhytidenglerula","local":"麻皺膠皿煤菌屬"},"region":"Taiwan","isEndemic":false,"isAlien":true,"habitat":[],"conservationStatus":"N","cites":"","iucn":"","meta":{"alienType":"native","rank":"Species"}},{"id":"taicol-t0043896","source":"taicol","sourceId":"t0043896","scientificName":"Schiffnerula villebrunneae","synonyms":[],"commonName":{"local":"褐毛謝爾膠皿煤菌"},"alias":{"local":""},"kingdom":{"scientific":"Fungi","local":"真菌界"},"phylum":{"scientific":"Ascomycota","local":"子囊菌門"},"taxonClass":{"scientific":"Dothideomycetes","local":"座囊菌綱"},"taxonOrder":{"scientific":"","local":""},"family":{"scientific":"Englerulaceae","local":""},"genus":{"scientific":"Schiffnerula","local":"謝爾膠皿煤菌屬"},"region":"Taiwan","isEndemic":false,"isAlien":true,"habitat":[],"conservationStatus":"N","cites":"","iucn":"","meta":{"alienType":"native","rank":"Species"}}]