[{"id":"taicol-t0043349","source":"taicol","sourceId":"t0043349","scientificName":"Pseudomassaria cyclobalanopsidis","synonyms":[],"commonName":{"local":"青剛櫟假黑團殼菌"},"alias":{"local":""},"kingdom":{"scientific":"Fungi","local":"真菌界"},"phylum":{"scientific":"Ascomycota","local":"子囊菌門"},"taxonClass":{"scientific":"Sordariomycetes","local":"糞殼菌綱"},"taxonOrder":{"scientific":"Xylariales","local":"炭角菌目"},"family":{"scientific":"Pseudomassariaceae","local":""},"genus":{"scientific":"Pseudomassaria","local":"假黑團殼菌屬"},"region":"Taiwan","isEndemic":false,"isAlien":true,"habitat":[],"conservationStatus":"N","cites":"","iucn":"","meta":{"alienType":"native","rank":"Species"}},{"id":"taicol-t0043350","source":"taicol","sourceId":"t0043350","scientificName":"Pseudomassaria islandica","synonyms":[],"commonName":{"local":"島嶼假黑團殼菌"},"alias":{"local":""},"kingdom":{"scientific":"Fungi","local":"真菌界"},"phylum":{"scientific":"Ascomycota","local":"子囊菌門"},"taxonClass":{"scientific":"Sordariomycetes","local":"糞殼菌綱"},"taxonOrder":{"scientific":"Xylariales","local":"炭角菌目"},"family":{"scientific":"Pseudomassariaceae","local":""},"genus":{"scientific":"Pseudomassaria","local":"假黑團殼菌屬"},"region":"Taiwan","isEndemic":false,"isAlien":true,"habitat":[],"conservationStatus":"N","cites":"","iucn":"","meta":{"alienType":"native","rank":"Species"}}]